autokoopman/__init__.py
autokoopman/__main__.py
autokoopman/_version.py
autokoopman/autokoopman.py
autokoopman/benchmark/__init__.py
autokoopman/benchmark/bio2.py
autokoopman/benchmark/fhn.py
autokoopman/benchmark/lalo20.py
autokoopman/benchmark/pendulum.py
autokoopman/benchmark/prde20.py
autokoopman/benchmark/robe21.py
autokoopman/benchmark/spring.py
autokoopman/core/__init__.py
autokoopman/core/estimator.py
autokoopman/core/format.py
autokoopman/core/scoring.py
autokoopman/core/system.py
autokoopman/core/trajectory.py
autokoopman/core/tuner.py
autokoopman/core/visualizer.py
autokoopman/estimator/__init__.py
autokoopman/estimator/deepkoopman.py
autokoopman/estimator/dmd.py
autokoopman/estimator/koopman.py
autokoopman/estimator/sindy.py
autokoopman/observable/__init__.py
autokoopman/observable/observables.py
autokoopman/observable/reweighted.py
autokoopman/observable/rff.py
autokoopman/tuner/__init__.py
autokoopman/tuner/bayesianopt.py
autokoopman/tuner/gridsearch.py
autokoopman/tuner/montecarlo.py
test/__init__.py
test/unit_test/__init__.py
test/unit_test/test_autokoopman.py
test/unit_test/test_benchmark.py
test/unit_test/test_deepk.py
test/unit_test/test_import.py
test/unit_test/test_koopman.py
test/unit_test/test_sindy.py
test/unit_test/test_system.py
test/unit_test/test_trajectory.py
autokoopman-0.30.7.dist-info/LICENSE
autokoopman-0.30.7.dist-info/METADATA
autokoopman-0.30.7.dist-info/WHEEL
autokoopman-0.30.7.dist-info/top_level.txt
autokoopman-0.30.7.dist-info/RECORD
