Metadata-Version: 2.1
Name: autokoopman
Version: 0.30.7
Summary: Automated Koopman Operator Linearization Library
Home-page: https://github.com/EthanJamesLew/AutoKoopman
Classifier: Programming Language :: Python :: 3
Classifier: License :: OSI Approved :: GNU General Public License v3 (GPLv3)
Classifier: Operating System :: OS Independent
Classifier: Topic :: Scientific/Engineering :: Artificial Intelligence
Classifier: Intended Audience :: Science/Research
Classifier: Topic :: Scientific/Engineering
Requires-Python: >=3.8
License-File: LICENSE
Requires-Dist: numpy >=1.19.0
Requires-Dist: matplotlib >=3.3.4
Requires-Dist: scipy >=1.5.4
Requires-Dist: sympy >=1.9
Requires-Dist: pandas >=1.1.5
Requires-Dist: scikit-learn >=1.0.2
Requires-Dist: tqdm >=4.62.2
Requires-Dist: pysindy ==1.7.2
